dvr_logger.py
dvr_mache.py
dvr_requester.py
setup.py
sdlib_v1.0.egg-info/PKG-INFO
sdlib_v1.0.egg-info/SOURCES.txt
sdlib_v1.0.egg-info/dependency_links.txt
sdlib_v1.0.egg-info/not-zip-safe
sdlib_v1.0.egg-info/requires.txt
sdlib_v1.0.egg-info/top_level.txt